PopularNews/__init__.py
PopularNewsIndonesia-0.0.2.3.dist-info/LICENSE
PopularNewsIndonesia-0.0.2.3.dist-info/METADATA
PopularNewsIndonesia-0.0.2.3.dist-info/WHEEL
PopularNewsIndonesia-0.0.2.3.dist-info/top_level.txt
PopularNewsIndonesia-0.0.2.3.dist-info/RECORD
