Metadata-Version: 2.1
Name: PopularNewsIndonesia
Version: 0.0.2.3
Summary: A simple package to show 5 popular news from detik.com
Author-email: Dwiky <damaradwiky6@gmail.com>
Project-URL: Homepage, https://github.com/DwikyDamara/popular-news-indonesia
Project-URL: Bug Tracker, https://github.com/DwikyDamara/popular-news-indonesia/issues
Classifier: Programming Language :: Python :: 3
Classifier: License :: OSI Approved :: GNU Affero General Public License v3
Classifier: Operating System :: OS Independent
Classifier: Development Status :: 4 - Beta
Requires-Python: >=3.7
License-File: LICENSE
